setup.py
src/aliyun_sdk_common_managed_credentials_provider.egg-info/PKG-INFO
src/aliyun_sdk_common_managed_credentials_provider.egg-info/SOURCES.txt
src/aliyun_sdk_common_managed_credentials_provider.egg-info/dependency_links.txt
src/aliyun_sdk_common_managed_credentials_provider.egg-info/requires.txt
src/aliyun_sdk_common_managed_credentials_provider.egg-info/top_level.txt
src/aliyun_sdk_secretsmanager_common_plugin/__init__.py
src/aliyun_sdk_secretsmanager_common_plugin/ak_expire_handler.py
src/aliyun_sdk_secretsmanager_common_plugin/aliyun_sdk_secretsmanager_plugins_manager.py
src/aliyun_sdk_secretsmanager_common_plugin/default_ak_expire_handler.py
src/aliyun_sdk_secretsmanager_common_plugin/secretsmanager_plugin_builder.py
src/aliyun_sdk_secretsmanager_common_plugin/secretsmanager_plugin_credential_updater.py
src/aliyun_sdk_secretsmanager_common_plugin/auth/__init__.py
src/aliyun_sdk_secretsmanager_common_plugin/auth/secretsmanager_plugin_credentials.py
src/aliyun_sdk_secretsmanager_common_plugin/model/__init__.py
src/aliyun_sdk_secretsmanager_common_plugin/model/monitor_message_info.py
src/aliyun_sdk_secretsmanager_common_plugin/model/secretsmanager_plugin_credentials_provider.py
src/aliyun_sdk_secretsmanager_common_plugin/service/__init__.py
src/aliyun_sdk_secretsmanager_common_plugin/service/default_plugins_credentials_loader.py
src/aliyun_sdk_secretsmanager_common_plugin/service/default_secretsmanager_plugin_cache_hook.py
src/aliyun_sdk_secretsmanager_common_plugin/service/monitor_cache_secret_store_strategy.py
src/aliyun_sdk_secretsmanager_common_plugin/service/monitor_memory_cache_secret_store_strategy.py
src/aliyun_sdk_secretsmanager_common_plugin/service/rotate_ak_secret_refresh_secret_strategy.py
src/aliyun_sdk_secretsmanager_common_plugin/service/secret_exchange.py
src/aliyun_sdk_secretsmanager_common_plugin/service/secret_recovery_strategy.py
src/aliyun_sdk_secretsmanager_common_plugin/service/secretsmanager_plugin_cache_hook.py
src/aliyun_sdk_secretsmanager_common_plugin/service/secretsmanager_plugin_credentials_loader.py
src/aliyun_sdk_secretsmanager_common_plugin/utils/__init__.py
src/aliyun_sdk_secretsmanager_common_plugin/utils/config_loader.py
src/aliyun_sdk_secretsmanager_common_plugin/utils/consts.py
src/aliyun_sdk_secretsmanager_common_plugin/utils/credentials_utils.py
