Metadata-Version: 1.2
Name: aliyun-sdk-common-managed-credentials-provider
Version: 0.1.1
Summary: Aliyun SDK Common Managed Credentials Provider
Home-page: UNKNOWN
Author: Aliyun
Maintainer: Aliyun
License: Apache License 2.0
Keywords: aliyun,kms,common
Platform: UNKNOWN
Classifier: Development Status :: 5 - Production/Stable
Classifier: Programming Language :: Python
Classifier: Programming Language :: Python :: 2
Classifier: Programming Language :: Python :: 2.7
Classifier: Programming Language :: Python :: 3
Classifier: Programming Language :: Python :: 3.6
Classifier: Programming Language :: Python :: 3.7
Classifier: Programming Language :: Python :: 3.8
Classifier: Programming Language :: Python :: 3.9
Classifier: Programming Language :: Python :: Implementation :: CPython
Classifier: Topic :: Security
